ejercicio_03/ejercicio3.v

module tabla1(input wire a,b,c, output wire y);

  assign y = ~a & ~c | a & c | ~b & ~c;
              
endmodule

module tabla2(input wire a,b,c, output wire y1);

  assign y1 = ~b;
              
endmodule
module tabla3(input wire a,b,c,d, output wire y2);

  assign y2 = ~a & ~b & ~c & ~d | a & b & ~c & ~d | a & ~b & c &~d | ~a & b & ~c & d | a & ~b & ~c & d| ~a & ~b & c & d | a & b & c & d | ~a & b & c & ~d;
              
endmodule
module tabla4(input wire a,b,c,d, output wire y3);

  assign y3 = a & ~d |b & d | a & c;
endmodule

ejercicio_03/ejercicio3_tb.v


module testbench();

// Variables para probar el módulo sillyFunction
reg a1, b1, c1, d1;
wire y,y1,y2, y3;

tabla1 U2(a1, b1, c1, y);
tabla2 U3(a1, b1, c1, y1);
tabla3 u4(a1, b1, c1, d1, y2);
tabla4 u5(a1, b1, c1, d1, y3);
initial begin
  $display("Tabla 1 y 2");  
  $display("a b c | y1 | y2");
  $display("------|----|");
  $monitor("%b %b %b | %b |%b", a1, b1, c1, y,y1);
     a1 = 0; b1 = 0; c1 = 0;
  #1 a1 = 0; b1 = 0; c1 = 1;
  #1 a1 = 0; b1 = 1; c1 = 0;
  #1 a1 = 0; b1 = 1; c1 = 1;
  #1 a1 = 1; b1 = 0; c1 = 0;
  #1 a1 = 1; b1 = 0; c1 = 1;
  #1 a1 = 1; b1 = 1; c1 = 0;
  #1 a1 = 1; b1 = 1; c1 = 1;
end
initial begin
#10
  $display("Tabla 3 y 4");  
  $display("a b c d |y | y2");
  $display("--------|--|----");
  $monitor("%b %b %b %b |%b | %b", a1, b1, c1, d1,y2 ,y3);
    a1=0; b1 = 0; c1 = 0; d1 = 0;
  #1 b1 = 0; c1 = 0; d1 = 1;
  #1 b1 = 0; c1 = 1; d1 = 0;
  #1 b1 = 0; c1 = 1; d1 = 1;
  #1 b1 = 1; c1 = 0; d1 = 0;
  #1 b1 = 1; c1 = 0; d1 = 1;
  #1 b1 = 1; c1 = 1; d1 = 0;
  #1 b1 = 1; c1 = 1; d1 = 1;
  #1 a1=1;b1 = 0; c1 = 0; d1 = 1;
  #1 b1 = 0; c1 = 1; d1 = 0;
  #1 b1 = 0; c1 = 1; d1 = 1;
  #1 b1 = 1; c1 = 0; d1 = 0;
  #1 b1 = 1; c1 = 0; d1 = 1;
  #1 b1 = 1; c1 = 1; d1 = 0;
  #1 b1 = 1; c1 = 1; d1 = 1;
end
initial
  #50 $finish;

initial begin
  $dumpfile("ejercicio3_tb.vcd");
  $dumpvars(0, testbench);
end

endmodule

ejercicio_03/ejercicio3_tb.vcd
$date
	Sun Aug 09 22:18:39 2020
$end
$version
	Icarus Verilog
$end
$timescale
	1ps
$end
$scope module testbench $end
$var wire 1 ! y3 $end
$var wire 1 " y2 $end
$var wire 1 # y1 $end
$var wire 1 $ y $end
$var reg 1 % a1 $end
$var reg 1 & b1 $end
$var reg 1 ' c1 $end
$var reg 1 ( d1 $end
$scope module U2 $end
$var wire 1 % a $end
$var wire 1 & b $end
$var wire 1 ' c $end
$var wire 1 $ y $end
$upscope $end
$scope module U3 $end
$var wire 1 % a $end
$var wire 1 & b $end
$var wire 1 ' c $end
$var wire 1 # y1 $end
$upscope $end
$scope module u4 $end
$var wire 1 % a $end
$var wire 1 & b $end
$var wire 1 ' c $end
$var wire 1 ( d $end
$var wire 1 " y2 $end
$upscope $end
$scope module u5 $end
$var wire 1 % a $end
$var wire 1 & b $end
$var wire 1 ' c $end
$var wire 1 ( d $end
$var wire 1 ! y3 $end
$upscope $end
$upscope $end
$enddefinitions $end
#0
$dumpvars
x(
0'
0&
0%
1$
1#
x"
0!
$end
#1
0$
1'
#2
x"
1$
x!
0#
0'
1&
#3
0$
1'
#4
x"
1$
1#
0'
0&
1%
#5
x"
1!
1'
#6
x"
0$
x!
0#
0'
1&
#7
1$
1!
1'
#10
1"
0!
1#
0(
0'
0&
0%
#11
0"
1(
#12
0$
0(
1'
#13
1"
1(
#14
0"
1$
0#
0(
0'
1&
#15
1"
1!
1(
#16
0$
0!
0(
1'
#17
0"
1!
1(
#18
1"
1$
0!
1#
0'
0&
1%
#19
1"
1!
0(
1'
#20
0"
1(
#21
1"
0$
1!
0#
0(
0'
1&
#22
0"
1(
#23
1$
0(
1'
#24
1"
1(
